DPZ/__init__.py
DPZ/dolar_price.py
DPZ/config/__init__.py
DPZ/config/driver_config.py
DPZ/sources/__init__.py
DPZ/sources/base.py
DPZ/sources/bcv.py
DPZ/sources/dolartoday.py
DPZ/sources/monitordolar.py
DPZ/sources/urls.py
DPZ-0.1.0.dist-info/LICENSE
DPZ-0.1.0.dist-info/METADATA
DPZ-0.1.0.dist-info/WHEEL
DPZ-0.1.0.dist-info/top_level.txt
DPZ-0.1.0.dist-info/RECORD
