Metadata-Version: 2.1
Name: DPZ
Version: 0.1.0
Summary: Obtén el precio del dólar en Venezuela desde múltiples fuentes con una sola línea de código! Con funciones de webscraping integradas, recopilamos y consolidamos los datos más actualizados
Home-page: https://github.com/AntonioVilaV/dolar-price-vzla
Author: Antonio Vila
Author-email: Antonio Vila <vila.antoniojose@gmail.com>
License: MIT License
Keywords: dolar,price,vzla,venezuela,divisa
Classifier: Intended Audience :: Developers
Classifier: License :: OSI Approved :: MIT License
Classifier: Operating System :: OS Independent
Classifier: Programming Language :: Python
Classifier: Topic :: Software Development :: Libraries :: Python Modules
Requires-Python: >=3.6
License-File: LICENSE
Requires-Dist: beautifulsoup4 >=4.12.3
Requires-Dist: requests >=2.31.0
Requires-Dist: selenium >=4.17.2
Requires-Dist: lxml >=5.1.0
